{
  "extends": "tslint:recommended",
  "rules": {
    "ordered-imports": [false],
    "object-literal-sort-keys": false,
    "trailing-comma": [true, {"multiline": "never", "singleline": "never"}],
    "await-promise": true,
    "forin": false,
    "interface-name": [false],
    "only-arrow-functions": [true, "allow-declarations", "allow-named-functions"],
    "arrow-parens":false,
    "prefer-const": false,
    "no-unbound-method": true,
    "typedef": [
      true,
      "member-variable-declaration",
      "parameter",
      "property-declaration"
    ],
    "quotemark": [true, "single"],
    "indent": [true, "spaces"],
    "max-line-length": [true, 120],
    "no-console": false,
    "no-bitwise": false,
    "variable-name" : false
  }
}
